lsyflaskmicroapp_ueditor/__init__.py
lsyflaskmicroapp_ueditor/config.py
lsyflaskmicroapp_ueditor/orm.py
lsyflaskmicroapp_ueditor/apis/__init__.py
lsyflaskmicroapp_ueditor/apis/file_upload.py
lsyflaskmicroapp_ueditor/apis/ueditor_file.py
lsyflaskmicroapp_ueditor/entitys/__init__.py
lsyflaskmicroapp_ueditor/entitys/ueditor_file.py
lsyflaskmicroapp_ueditor/models/__init__.py
lsyflaskmicroapp_ueditor/models/ueditor_file.py
lsyflaskmicroapp_ueditor/schemas/__init__.py
lsyflaskmicroapp_ueditor/schemas/ueditor_file.py
lsyflaskmicroapp_ueditor-1.0.0.dist-info/METADATA
lsyflaskmicroapp_ueditor-1.0.0.dist-info/WHEEL
lsyflaskmicroapp_ueditor-1.0.0.dist-info/top_level.txt
lsyflaskmicroapp_ueditor-1.0.0.dist-info/RECORD
