Metadata-Version: 2.1
Name: lsyflaskmicroapp-ueditor
Version: 1.0.0
Summary: lsyflaskmicroapp_ueditor
Home-page: https://gitee.com/linkeddt/lsyflaskmicroapp_ueditor.git
Author: fhp
Author-email: chinafengheping@outlook.com
License: UNKNOWN
Platform: UNKNOWN
Requires-Dist: lsyflasksdkcore (==1.0.2)
Requires-Dist: lsyflaskplugin-minio (==1.0.0)
Requires-Dist: SQLAlchemy (==1.3.15)
Requires-Dist: Flask-SQLAlchemy (==2.5.1)
